Metadata-Version: 1.0
Name: swiss
Version: 0.3
Summary: Swiss Army Knife for Data Work
Home-page: http://knowledgeforge.net/okfn/swiss/
Author: Open Knowledge Foundation
Author-email: info@okfn.org
License: MIT
Download-URL: http://knowledgeforge.net/okfn/swiss/
Platform: UNKNOWN
Classifier: Development Status :: 5 - Production/Stable
Classifier: Environment :: Console
Classifier: Intended Audience :: Developers
Classifier: Operating System :: OS Independent
Classifier: Programming Language :: Python
Classifier: Topic :: Software Development :: Libraries :: Python Modules
